{"day":"2026-06-20","requests_today":34,"fixture_map":{"537391":{"fixture_id":1489383,"home_id":2,"away_id":13},"537392":{"fixture_id":1539016,"home_id":1567,"away_id":1090},"537397":{"fixture_id":1489381,"home_id":26,"away_id":1532},"537398":{"fixture_id":1489382,"home_id":775,"away_id":1548},"537403":{"fixture_id":1539003,"home_id":27,"away_id":1508},"537409":{"fixture_id":1489384,"home_id":10,"away_id":3},"537410":{"fixture_id":1489385,"home_id":1504,"away_id":11},"537404":{"fixture_id":1489386,"home_id":1568,"away_id":8},"537329":{"fixture_id":1539004,"home_id":770,"away_id":1531},"537335":{"fixture_id":1539005,"home_id":15,"away_id":1113},"537336":{"fixture_id":1489387,"home_id":5529,"away_id":1569},"537330":{"fixture_id":1489388,"home_id":16,"away_id":17},"537348":{"fixture_id":1489391,"home_id":2384,"away_id":20},"537342":{"fixture_id":1489390,"home_id":1108,"away_id":31},"537341":{"fixture_id":1489389,"home_id":6,"away_id":2386},"537347":{"fixture_id":1539006,"home_id":777,"away_id":2380},"537359":{"fixture_id":1539007,"home_id":1118,"away_id":5}},"events":{"537391":{"goals_detail":[{"minute":"66","scorer":"K. Mbappe","team":"France","assist":"M. Olise","type":"NORMAL"},{"minute":"82","scorer":"B. Barcola","team":"France","assist":"A. Rabiot","type":"NORMAL"},{"minute":"90","scorer":"I. Mbaye","team":"Senegal","assist":"I. Ndiaye","type":"NORMAL"},{"minute":"90","scorer":"K. Mbappe","team":"France","assist":"","type":"NORMAL"}],"bookings":[],"substitutions":[{"minute":"75","player_in":"I. Sarr","player_out":"I. Mbaye","team":"Senegal"},{"minute":"76","player_in":"L. Camara","player_out":"H. Diarra","team":"Senegal"},{"minute":"80","player_in":"O. Dembele","player_out":"B. Barcola","team":"France"},{"minute":"83","player_in":"N. Jackson","player_out":"B. Dieng","team":"Senegal"},{"minute":"83","player_in":"P. Gueye","player_out":"I. Ndiaye","team":"Senegal"},{"minute":"87","player_in":"D. Doue","player_out":"R. Cherki","team":"France"},{"minute":"88","player_in":"I. Gueye","player_out":"P. Ciss","team":"Senegal"}],"status":"FINISHED","last_fetch":"2026-06-20T15:43:25.173030+00:00"},"537392":{"goals_detail":[{"minute":"29","scorer":"E. Haaland","team":"Norway","assist":"D. Wolfe","type":"NORMAL"},{"minute":"39","scorer":"A. Hussein","team":"Iraq","assist":"A. Al Ammari","type":"NORMAL"},{"minute":"43","scorer":"E. Haaland","team":"Norway","assist":"","type":"NORMAL"},{"minute":"76","scorer":"L. Ostigard","team":"Norway","assist":"M. Odegaard","type":"NORMAL"},{"minute":"90","scorer":"A. Hussein","team":"Norway","assist":"","type":"OWN"}],"bookings":[{"minute":"86","player":"Zaid Tahseen","team":"Iraq","card":"YELLOW"}],"substitutions":[{"minute":"59","player_in":"Z. Ismaeel","player_out":"Z. Iqbal","team":"Iraq"},{"minute":"59","player_in":"A. Al Hamadi","player_out":"M. Farji","team":"Iraq"},{"minute":"73","player_in":"A. Jasim","player_out":"A. Qasem","team":"Iraq"},{"minute":"73","player_in":"H. Ali","player_out":"M. Saadoon","team":"Iraq"},{"minute":"73","player_in":"A. Sorloth","player_out":"O. Bobb","team":"Norway"},{"minute":"73","player_in":"D. Wolfe","player_out":"L. Ostigard","team":"Norway"},{"minute":"73","player_in":"F. Aursnes","player_out":"K. Thorstvedt","team":"Norway"},{"minute":"73","player_in":"A. Nusa","player_out":"A. Schjelderup","team":"Norway"},{"minute":"78","player_in":"I. Bayesh","player_out":"Meme","team":"Iraq"},{"minute":"81","player_in":"M. Odegaard","player_out":"P. Berg","team":"Norway"}],"status":"FINISHED","last_fetch":"2026-06-20T15:43:25.173030+00:00"},"537397":{"goals_detail":[{"minute":"17","scorer":"L. Messi","team":"Argentina","assist":"R. de Paul","type":"NORMAL"},{"minute":"60","scorer":"L. Messi","team":"Argentina","assist":"","type":"NORMAL"},{"minute":"76","scorer":"L. Messi","team":"Argentina","assist":"N. Gonzalez","type":"NORMAL"}],"bookings":[],"substitutions":[{"minute":"46","player_in":"G. Montiel","player_out":"N. Molina","team":"Argentina"},{"minute":"55","player_in":"T. Almada","player_out":"N. Gonzalez","team":"Argentina"},{"minute":"55","player_in":"L. Martinez","player_out":"J. Alvarez","team":"Argentina"},{"minute":"64","player_in":"A. Hadj Moussa","player_out":"R. Mahrez","team":"Algeria"},{"minute":"64","player_in":"H. Boudaoui","player_out":"H. Aouar","team":"Algeria"},{"minute":"64","player_in":"A. Gouiri","player_out":"M. Amoura","team":"Algeria"},{"minute":"80","player_in":"C. Romero","player_out":"N. Otamendi","team":"Argentina"},{"minute":"80","player_in":"L. Messi","player_out":"N. Paz","team":"Argentina"},{"minute":"81","player_in":"N. Bentaleb","player_out":"A. Boulbina","team":"Algeria"},{"minute":"82","player_in":"I. Maza","player_out":"R. Zerrouki","team":"Algeria"}],"status":"FINISHED","last_fetch":"2026-06-20T15:43:25.173030+00:00"},"537398":{"goals_detail":[{"minute":"21","scorer":"R. Schmid","team":"Austria","assist":"X. Schlager","type":"NORMAL"},{"minute":"50","scorer":"A. Olwan","team":"Jordan","assist":"N. Al Rawabdeh","type":"NORMAL"},{"minute":"76","scorer":"Y. Al Arab","team":"Austria","assist":"","type":"OWN"},{"minute":"90","scorer":"M. Arnautovic","team":"Austria","assist":"","type":"PENALTY"}],"bookings":[{"minute":"77","player":"Marcel Sabitzer","team":"Austria","card":"YELLOW"}],"substitutions":[{"minute":"46","player_in":"S. Kalajdzic","player_out":"M. Arnautovic","team":"Austria"},{"minute":"59","player_in":"P. Mwene","player_out":"P. Wanner","team":"Austria"},{"minute":"59","player_in":"D. Alaba","player_out":"K. Danso","team":"Austria"},{"minute":"59","player_in":"X. Schlager","player_out":"C. Chukwuemeka","team":"Austria"},{"minute":"72","player_in":"M. Abualnadi","player_out":"S. Obaid","team":"Jordan"},{"minute":"81","player_in":"A. Nasib","player_out":"S. Al Rosan","team":"Jordan"},{"minute":"81","player_in":"E. Haddad","player_out":"M. Al Mardi","team":"Jordan"},{"minute":"83","player_in":"R. Schmid","player_out":"P. Wimmer","team":"Austria"},{"minute":"88","player_in":"M. Tamari","player_out":"M. Al Daoud","team":"Jordan"},{"minute":"89","player_in":"O. Al Fakhouri","player_out":"A. Azaizeh","team":"Jordan"}],"status":"FINISHED","last_fetch":"2026-06-20T15:43:25.173030+00:00"},"537403":{"goals_detail":[{"minute":"6","scorer":"J. Neves","team":"Portugal","assist":"P. Neto","type":"NORMAL"},{"minute":"45","scorer":"Y. Wissa","team":"Congo DR","assist":"A. Masuaku","type":"NORMAL"}],"bookings":[{"minute":"13","player":"Bernardo Silva","team":"Portugal","card":"YELLOW"},{"minute":"32","player":"Chancel Mbemba","team":"Congo DR","card":"YELLOW"},{"minute":"88","player":"Nélson Semedo","team":"Portugal","card":"YELLOW"},{"minute":"90+2","player":"Tomás Araújo","team":"Portugal","card":"YELLOW"}],"substitutions":[{"minute":"46","player_in":"B. Silva","player_out":"F. Conceicao","team":"Portugal"},{"minute":"57","player_in":"N. Mukau","player_out":"N. Sadiki","team":"Congo DR"},{"minute":"71","player_in":"P. Neto","player_out":"R. Leao","team":"Portugal"},{"minute":"72","player_in":"N. Mendes","player_out":"N. Semedo","team":"Portugal"},{"minute":"74","player_in":"A. Masuaku","player_out":"J. Kayembe","team":"Congo DR"},{"minute":"74","player_in":"E. Kayembe","player_out":"C. Pickel","team":"Congo DR"},{"minute":"83","player_in":"Vitinha","player_out":"G. Ramos","team":"Portugal"},{"minute":"85","player_in":"A. Wan-Bissaka","player_out":"G. Kalulu","team":"Congo DR"},{"minute":"85","player_in":"C. Bakambu","player_out":"S. Banza","team":"Congo DR"}],"status":"FINISHED","last_fetch":"2026-06-20T15:43:25.173030+00:00"},"537409":{"goals_detail":[{"minute":"12","scorer":"H. Kane","team":"England","assist":"","type":"PENALTY"},{"minute":"36","scorer":"M. Baturina","team":"Croatia","assist":"P. Sucic","type":"NORMAL"},{"minute":"42","scorer":"H. Kane","team":"England","assist":"D. Rice","type":"NORMAL"},{"minute":"45","scorer":"P. Musa","team":"Croatia","assist":"I. Perisic","type":"NORMAL"},{"minute":"47","scorer":"J. Bellingham","team":"England","assist":"E. Anderson","type":"NORMAL"},{"minute":"85","scorer":"M. Rashford","team":"England","assist":"B. Saka","type":"NORMAL"}],"bookings":[],"substitutions":[{"minute":"58","player_in":"L. Modric","player_out":"M. Kovacic","team":"Croatia"},{"minute":"66","player_in":"L. Vuskovic","player_out":"M. Pasalic","team":"Croatia"},{"minute":"66","player_in":"P. Musa","player_out":"I. Matanovic","team":"Croatia"},{"minute":"72","player_in":"D. Rice","player_out":"M. Rogers","team":"England"},{"minute":"72","player_in":"N. Madueke","player_out":"B. Saka","team":"England"},{"minute":"72","player_in":"A. Gordon","player_out":"M. Rashford","team":"England"},{"minute":"78","player_in":"M. Pasalic","player_out":"A. Kramaric","team":"Croatia"},{"minute":"78","player_in":"M. Baturina","player_out":"N. Vlasic","team":"Croatia"},{"minute":"80","player_in":"J. Bellingham","player_out":"D. Spence","team":"England"},{"minute":"87","player_in":"J. Stones","player_out":"M. Guehi","team":"England"}],"status":"FINISHED","last_fetch":"2026-06-20T15:43:25.173030+00:00"},"537410":{"goals_detail":[{"minute":"90","scorer":"C. Yirenkyi","team":"Ghana","assist":"","type":"NORMAL"}],"bookings":[{"minute":"16","player":"Caleb Yirenkyi","team":"Ghana","card":"YELLOW"},{"minute":"72","player":"César Blackman","team":"Panama","card":"YELLOW"},{"minute":"90+9","player":"Carlos Harvey","team":"Panama","card":"YELLOW"}],"substitutions":[{"minute":"46","player_in":"L. Ati Zigi","player_out":"B. Asare","team":"Ghana"},{"minute":"58","player_in":"K. Sulemana","player_out":"B. Thomas-Asante","team":"Ghana"},{"minute":"58","player_in":"E. Nuamah","player_out":"I. Fatawu","team":"Ghana"},{"minute":"63","player_in":"C. Waterman","player_out":"J. Fajardo","team":"Panama"},{"minute":"63","player_in":"C. Martinez","player_out":"A. Londono","team":"Panama"},{"minute":"74","player_in":"J. Rodriguez","player_out":"I. Diaz","team":"Panama"},{"minute":"78","player_in":"E. Owusu","player_out":"K. Sibo","team":"Ghana"},{"minute":"87","player_in":"J. Ayew","player_out":"P. Adu","team":"Ghana"},{"minute":"90","player_in":"C. Blackman","player_out":"A. Godoy","team":"Panama"}],"status":"FINISHED","last_fetch":"2026-06-20T15:43:25.173030+00:00"},"537404":{"goals_detail":[{"minute":"40","scorer":"D. Munoz","team":"Colombia","assist":"L. Diaz","type":"NORMAL"},{"minute":"60","scorer":"A. Fayzullaev","team":"Uzbekistan","assist":"","type":"NORMAL"},{"minute":"65","scorer":"L. Diaz","team":"Colombia","assist":"G. Puerta","type":"NORMAL"},{"minute":"90","scorer":"J. Campaz","team":"Colombia","assist":"C. Hernandez","type":"NORMAL"}],"bookings":[{"minute":"7","player":"Johan Mojica","team":"Colombia","card":"YELLOW"},{"minute":"34","player":"Abdukodir Khusanov","team":"Uzbekistan","card":"YELLOW"}],"substitutions":[{"minute":"46","player_in":"O. Urunov","player_out":"D. Khamdamov","team":"Uzbekistan"},{"minute":"46","player_in":"S. Nasrullaev","player_out":"F. Sayfiev","team":"Uzbekistan"},{"minute":"72","player_in":"J. Rodriguez","player_out":"J. Campaz","team":"Colombia"},{"minute":"77","player_in":"A. Fayzullaev","player_out":"A. Amonov","team":"Uzbekistan"},{"minute":"77","player_in":"R. Ashurmatov","player_out":"J. Urozov","team":"Uzbekistan"},{"minute":"80","player_in":"L. Suarez","player_out":"C. Hernandez","team":"Colombia"},{"minute":"80","player_in":"G. Puerta","player_out":"R. Rios","team":"Colombia"},{"minute":"90+3","player_in":"E. Shomurodov","player_out":"I. Sergeev","team":"Uzbekistan"},{"minute":"90+3","player_in":"J. Arias","player_out":"K. Castano","team":"Colombia"},{"minute":"90+3","player_in":"L. Diaz","player_out":"A. Gomez","team":"Colombia"}],"status":"FINISHED","last_fetch":"2026-06-20T15:43:25.173030+00:00"},"537329":{"goals_detail":[{"minute":"6","scorer":"M. Sadilek","team":"Czechia","assist":"A. Sojka","type":"NORMAL"},{"minute":"83","scorer":"T. Mokoena","team":"South Africa","assist":"","type":"PENALTY"}],"bookings":[{"minute":"33","player":"Teboho Mokoena","team":"South Africa","card":"YELLOW"},{"minute":"40","player":"Thalente Mbatha","team":"South Africa","card":"YELLOW"},{"minute":"75","player":"Ladislav Krejčí","team":"Czechia","card":"YELLOW"}],"substitutions":[{"minute":"46","player_in":"J. Adams","player_out":"R. Mofokeng","team":"South Africa"},{"minute":"55","player_in":"A. Sojka","player_out":"J. Zeleny","team":"Czechia"},{"minute":"55","player_in":"V. Darida","player_out":"P. Sulc","team":"Czechia"},{"minute":"66","player_in":"I. Rayners","player_out":"E. Makgopa","team":"South Africa"},{"minute":"67","player_in":"A. Hlozek","player_out":"L. Provod","team":"Czechia"},{"minute":"67","player_in":"M. Sadilek","player_out":"T. Soucek","team":"Czechia"},{"minute":"78","player_in":"L. Cerv","player_out":"D. Zima","team":"Czechia"},{"minute":"84","player_in":"T. Maseko","player_out":"K. Sebelebele","team":"South Africa"}],"status":"FINISHED","last_fetch":"2026-06-20T15:43:25.173030+00:00"},"537335":{"goals_detail":[{"minute":"74","scorer":"J. Manzambi","team":"Switzerland","assist":"","type":"NORMAL"},{"minute":"84","scorer":"R. Vargas","team":"Switzerland","assist":"B. Embolo","type":"NORMAL"},{"minute":"90","scorer":"J. Manzambi","team":"Switzerland","assist":"R. Vargas","type":"NORMAL"},{"minute":"90","scorer":"E. Mahmic","team":"Bosnia-H.","assist":"","type":"NORMAL"},{"minute":"90","scorer":"G. Xhaka","team":"Switzerland","assist":"","type":"PENALTY"}],"bookings":[{"minute":"59","player":"Amar Dedić","team":"Bosnia-H.","card":"YELLOW"},{"minute":"61","player":"Edin Džeko","team":"Bosnia-H.","card":"YELLOW"},{"minute":"65","player":"Nico Elvedi","team":"Switzerland","card":"YELLOW"},{"minute":"80","player":"Tarik Muharemović","team":"Bosnia-H.","card":"RED"}],"substitutions":[{"minute":"63","player_in":"B. Tahirovic","player_out":"I. Basic","team":"Bosnia-H."},{"minute":"64","player_in":"E. Dzeko","player_out":"E. Bajraktarevic","team":"Bosnia-H."},{"minute":"71","player_in":"M. Aebischer","player_out":"D. Sow","team":"Switzerland"},{"minute":"71","player_in":"F. Rieder","player_out":"R. Vargas","team":"Switzerland"},{"minute":"71","player_in":"D. Ndoye","player_out":"J. Manzambi","team":"Switzerland"},{"minute":"86","player_in":"S. Widmer","player_out":"L. Jaquez","team":"Switzerland"},{"minute":"86","player_in":"E. Demirovic","player_out":"J. Lukic","team":"Bosnia-H."},{"minute":"86","player_in":"I. Sunjic","player_out":"A. Hadziahmetovic","team":"Bosnia-H."},{"minute":"89","player_in":"B. Embolo","player_out":"C. Itten","team":"Switzerland"},{"minute":"90+1","player_in":"K. Alajbegovic","player_out":"E. Mahmic","team":"Bosnia-H."}],"status":"FINISHED","last_fetch":"2026-06-20T15:43:25.173030+00:00"},"537336":{"goals_detail":[{"minute":"16","scorer":"C. Larin","team":"Canada","assist":"","type":"NORMAL"},{"minute":"29","scorer":"J. David","team":"Canada","assist":"","type":"NORMAL"},{"minute":"33","scorer":"","team":"Canada","assist":"","type":"NORMAL"},{"minute":"45","scorer":"J. David","team":"Canada","assist":"","type":"NORMAL"},{"minute":"64","scorer":"N. Saliba","team":"Canada","assist":"","type":"NORMAL"},{"minute":"75","scorer":"M. Al Mannai","team":"Canada","assist":"","type":"OWN"},{"minute":"90","scorer":"J. David","team":"Canada","assist":"N. Saliba","type":"NORMAL"}],"bookings":[{"minute":"9","player":"Derek Cornelius","team":"Canada","card":"YELLOW"},{"minute":"33","player":"Homam Al-Amin","team":"Qatar","card":"RED"},{"minute":"53","player":"Assim Madibo","team":"Qatar","card":"RED"},{"minute":"62","player":"Ahmed Fathi","team":"Qatar","card":"YELLOW"}],"substitutions":[{"minute":"40","player_in":"Y. Abdurisag","player_out":"S. Al Brake","team":"Qatar"},{"minute":"46","player_in":"D. Cornelius","player_out":"M. Bombito","team":"Canada"},{"minute":"46","player_in":"Edmilson Junior","player_out":"A. Fathi","team":"Qatar"},{"minute":"46","player_in":"J. Gaber","player_out":"M. Al Mannai","team":"Qatar"},{"minute":"57","player_in":"I. Kone","player_out":"N. Saliba","team":"Canada"},{"minute":"59","player_in":"A. Afif","player_out":"A. Al Hussain","team":"Qatar"},{"minute":"71","player_in":"L. De Fougerolles","player_out":"J. Shaffelburg","team":"Canada"},{"minute":"71","player_in":"A. Ahmed","player_out":"T. Oluwaseyi","team":"Canada"},{"minute":"83","player_in":"T. Buchanan","player_out":"N. Sigur","team":"Canada"},{"minute":"87","player_in":"","player_out":"Lucas Mendes","team":"Qatar"}],"status":"FINISHED","last_fetch":"2026-06-20T15:43:25.173030+00:00"},"537330":{"goals_detail":[{"minute":"50","scorer":"L. Romo","team":"Mexico","assist":"","type":"NORMAL"}],"bookings":[{"minute":"4","player":"Kang-in Lee","team":"Korea Republic","card":"YELLOW"},{"minute":"58","player":"Seung Ho Paik","team":"Korea Republic","card":"YELLOW"}],"substitutions":[{"minute":"57","player_in":"Lee Jae-Sung","player_out":"Hwang Hee-Chan","team":"Korea Republic"},{"minute":"57","player_in":"Son Heung-Min","player_out":"Oh Hyeon-Gyu","team":"Korea Republic"},{"minute":"71","player_in":"L. Romo","player_out":"O. Vargas","team":"Mexico"},{"minute":"71","player_in":"B. Gutierrez","player_out":"O. Pineda","team":"Mexico"},{"minute":"71","player_in":"Kim Moon-Hwan","player_out":"Eom Ji-Sung","team":"Korea Republic"},{"minute":"71","player_in":"Seol Young-Woo","player_out":"Yang Hyun-Jun","team":"Korea Republic"},{"minute":"77","player_in":"Paik Seung-Ho","player_out":"Cho Gue-Sung","team":"Korea Republic"},{"minute":"80","player_in":"R. Alvarado","player_out":"I. Reyes","team":"Mexico"},{"minute":"80","player_in":"R. Jimenez","player_out":"S. Gimenez","team":"Mexico"},{"minute":"84","player_in":"J. Quinones","player_out":"C. S. Huerta Valera","team":"Mexico"}],"status":"FINISHED","last_fetch":"2026-06-20T15:43:25.173030+00:00"},"537348":{"goals_detail":[{"minute":"11","scorer":"Cameron Burgess","team":"USA","assist":"","type":"OWN"},{"minute":"44","scorer":"Alexander Freeman","team":"USA","assist":"","type":"NORMAL"}],"bookings":[{"minute":"16","player":"Jordan Bos","team":"Australia","card":"YELLOW"},{"minute":"32","player":"Alessandro Circati","team":"Australia","card":"YELLOW"},{"minute":"56","player":"Antonee Robinson","team":"USA","card":"YELLOW"},{"minute":"89","player":"Folarin Balogun","team":"USA","card":"YELLOW"},{"minute":"89","player":"Harry Souttar","team":"Australia","card":"YELLOW"},{"minute":"89","player":"Jacob Italiano","team":"Australia","card":"YELLOW"},{"minute":"90+3","player":"Chris Richards","team":"USA","card":"YELLOW"}],"substitutions":[{"minute":"46","player_in":"Nishan Velupillay","player_out":"Connor Metcalfe","team":"Australia"},{"minute":"46","player_in":"Mohamed Touré","player_out":"Nestory Irankunda","team":"Australia"},{"minute":"46","player_in":"Cameron Burgess","player_out":"Jason Geria","team":"Australia"},{"minute":"61","player_in":"Mathew Leckie","player_out":"Cristian Volpato","team":"Australia"},{"minute":"74","player_in":"Ricardo Pepi","player_out":"Sebastian Berhalter","team":"USA"},{"minute":"78","player_in":"Paul Okon-Engstler","player_out":"Jackson Irvine","team":"Australia"},{"minute":"81","player_in":"Antonee Robinson","player_out":"Auston Trusty","team":"USA"},{"minute":"81","player_in":"Sergiño Dest","player_out":"Joe Scally","team":"USA"},{"minute":"90","player_in":"Weston McKennie","player_out":"Giovanni Reyna","team":"USA"},{"minute":"90","player_in":"Folarin Balogun","player_out":"Haji Wright","team":"USA"}],"status":"FINISHED","last_fetch":"2026-06-20T15:43:25.173030+00:00"},"537342":{"goals_detail":[{"minute":"2","scorer":"Ismael Saibari","team":"Morocco","assist":"Brahim Díaz","type":"NORMAL"}],"bookings":[{"minute":"23","player":"Issa Diop","team":"Morocco","card":"YELLOW"},{"minute":"66","player":"Andy Robertson","team":"Scotland","card":"YELLOW"}],"substitutions":[{"minute":"60","player_in":"Kieran Tierney","player_out":"Ben Gannon-Doak","team":"Scotland"},{"minute":"71","player_in":"Ryan Christie","player_out":"Kenny McLean","team":"Scotland"},{"minute":"71","player_in":"Che Adams","player_out":"Lyndon Dykes","team":"Scotland"},{"minute":"84","player_in":"Brahim Díaz","player_out":"Ayoube Amaimouni Echghouyab","team":"Morocco"},{"minute":"84","player_in":"Bilal El Khannouss","player_out":"Chemsdine Talbi","team":"Morocco"},{"minute":"84","player_in":"Ismael Saibari","player_out":"Soufiane Rahimi","team":"Morocco"},{"minute":"89","player_in":"John McGinn","player_out":"Ross Stewart","team":"Scotland"},{"minute":"89","player_in":"Nathan Patterson","player_out":"Tony Ralston","team":"Scotland"},{"minute":"90","player_in":"Azzedine Ounahi","player_out":"Samir El Mourabet","team":"Morocco"}],"status":"FINISHED","last_fetch":"2026-06-20T15:43:25.173030+00:00"},"537341":{"goals_detail":[{"minute":"23","scorer":"M. Cunha","team":"Brazil","assist":"","type":"NORMAL"},{"minute":"36","scorer":"M. Cunha","team":"Brazil","assist":"Vinicius Junior","type":"NORMAL"},{"minute":"45+3","scorer":"Vinicius Junior","team":"Brazil","assist":"Lucas Paqueta","type":"NORMAL"}],"bookings":[{"minute":"4","player":"C. Arcus","team":"Haiti","card":"YELLOW"},{"minute":"45+4","player":"F. Pierrot","team":"Haiti","card":"YELLOW"},{"minute":"65","player":"Douglas Santos","team":"Brazil","card":"YELLOW"},{"minute":"72","player":"D. Jean Jacques","team":"Haiti","card":"YELLOW"}],"substitutions":[{"minute":"40","player_in":"Raphinha","player_out":"Rayan","team":"Brazil"},{"minute":"46","player_in":"C. Arcus","player_out":"D. Simon","team":"Haiti"},{"minute":"46","player_in":"F. Pierrot","player_out":"W. Isidor","team":"Haiti"},{"minute":"62","player_in":"J. Casimir","player_out":"L. Deedson","team":"Haiti"},{"minute":"64","player_in":"Lucas Paqueta","player_out":"G. Martinelli","team":"Brazil"},{"minute":"64","player_in":"M. Cunha","player_out":"Endrick","team":"Brazil"},{"minute":"71","player_in":"R. Providence","player_out":"L. Joseph","team":"Haiti"},{"minute":"81","player_in":"Vinicius Junior","player_out":"Danilo Santos","team":"Brazil"},{"minute":"81","player_in":"Bruno Guimaraes","player_out":"Ederson","team":"Brazil"},{"minute":"81","player_in":"J. Bellegarde","player_out":"D. Etienne","team":"Haiti"}],"status":"FINISHED","last_fetch":"2026-06-20T15:43:25.173030+00:00"},"537347":{"goals_detail":[{"minute":"2","scorer":"M. Galarza","team":"Paraguay","assist":"J. Enciso","type":"NORMAL"}],"bookings":[{"minute":"4","player":"M. Galarza","team":"Paraguay","card":"YELLOW"},{"minute":"45+3","player":"M. Almiron","team":"Paraguay","card":"RED"},{"minute":"63","player":"V. Montella","team":"Turkey","card":"YELLOW"},{"minute":"71","player":"E. Elmali","team":"Turkey","card":"YELLOW"}],"substitutions":[{"minute":"46","player_in":"I. Pitta","player_out":"D. Bobadilla","team":"Paraguay"},{"minute":"46","player_in":"K. Akturkoglu","player_out":"B. Yilmaz","team":"Turkey"},{"minute":"60","player_in":"I. Yuksek","player_out":"C. Uzun","team":"Turkey"},{"minute":"60","player_in":"Y. Akgun","player_out":"D. Gul","team":"Turkey"},{"minute":"67","player_in":"D. Gomez","player_out":"G. Velazquez","team":"Paraguay"},{"minute":"70","player_in":"F. Kadioglu","player_out":"E. Elmali","team":"Turkey"},{"minute":"81","player_in":"J. Caceres","player_out":"A. Maidana","team":"Paraguay"},{"minute":"86","player_in":"A. Bardakci","player_out":"O. Kokcu","team":"Turkey"},{"minute":"90+2","player_in":"J. Enciso","player_out":"G. Avalos","team":"Paraguay"},{"minute":"90+2","player_in":"M. Galarza","player_out":"J. Canale","team":"Paraguay"}],"status":"FINISHED","last_fetch":"2026-06-20T15:43:25.173030+00:00"},"537359":{"goals_detail":[{"minute":"5","scorer":"B. Brobbey","team":"Netherlands","assist":"C. Gakpo","type":"NORMAL"},{"minute":"17","scorer":"B. Brobbey","team":"Netherlands","assist":"D. Dumfries","type":"NORMAL"}],"bookings":[],"substitutions":[],"status":"IN_PLAY","last_fetch":"2026-06-20T17:35:43.094756+00:00"}}}